[
  {
    "uid": "332066",
    "name": "张莉",
    "org_name": "上海万峰房地产有限公司",
    "org_type": "一般企业",
    "cert_type": "个人",
    "position": "总经理",
    "department": "投资部",
    "last_interaction_time": "2023-12-22 17:13:35",
    "last_interaction_behavior": "参会",
    "interaction_company": "长盛基金",
    "apply_count": 0,
    "apply_records": [],
    "attend_count": 1,
    "attend_records": [
      {
        "time": "2023-12-22",
        "meet_title": "【长盛基金】预见·机遇 长盛基金2022年投资策略会",
        "duration": 0
      }
    ],
    "is_first_attend": false,
    "subscribed_companies": [],
    "special_companies": ""
  }
]